skill_ovos_setup/LICENSE
skill_ovos_setup/MANIFEST.in
skill_ovos_setup/README.md
skill_ovos_setup/__init__.py
skill_ovos_setup/version.py
skill_ovos_setup/locale/de-de/dialog/backend.confirm.dialog
skill_ovos_setup/locale/de-de/dialog/backend.confirm.gui.dialog
skill_ovos_setup/locale/de-de/dialog/backend.confirm.intro.offline.dialog
skill_ovos_setup/locale/de-de/dialog/backend.confirm.intro.personal.dialog
skill_ovos_setup/locale/de-de/dialog/backend.confirm.intro.selene.dialog
skill_ovos_setup/locale/de-de/dialog/backend.intro.dialog
skill_ovos_setup/locale/de-de/dialog/backend.not.understood.dialog
skill_ovos_setup/locale/de-de/dialog/backend.options.intro.dialog
skill_ovos_setup/locale/de-de/dialog/backend.personal.url.prompt.dialog
skill_ovos_setup/locale/de-de/dialog/backend.prompt.dialog
skill_ovos_setup/locale/de-de/dialog/backend.selected.offline.dialog
skill_ovos_setup/locale/de-de/dialog/backend.selected.personal.dialog
skill_ovos_setup/locale/de-de/dialog/backend.selected.selene.dialog
skill_ovos_setup/locale/de-de/dialog/backend.selene.dialog
skill_ovos_setup/locale/de-de/dialog/choice.failed.dialog
skill_ovos_setup/locale/de-de/dialog/code.spelling.value
skill_ovos_setup/locale/de-de/dialog/error.unexpected.restarting.dialog
skill_ovos_setup/locale/de-de/dialog/language.menu.dialog
skill_ovos_setup/locale/de-de/dialog/options.backend.value
skill_ovos_setup/locale/de-de/dialog/options.select.gui.dialog
skill_ovos_setup/locale/de-de/dialog/options.stt.value
skill_ovos_setup/locale/de-de/dialog/options.tts.value
skill_ovos_setup/locale/de-de/dialog/pairing.already.paired.dialog
skill_ovos_setup/locale/de-de/dialog/pairing.code.dialog
skill_ovos_setup/locale/de-de/dialog/pairing.intro.dialog
skill_ovos_setup/locale/de-de/dialog/pairing.not.paired.dialog
skill_ovos_setup/locale/de-de/dialog/pairing.paired.dialog
skill_ovos_setup/locale/de-de/dialog/selection.ask.intro.dialog
skill_ovos_setup/locale/de-de/dialog/stt.confirm.dialog
skill_ovos_setup/ovos_skill_setup.egg-info/PKG-INFO
skill_ovos_setup/ovos_skill_setup.egg-info/SOURCES.txt
skill_ovos_setup/ovos_skill_setup.egg-info/dependency_links.txt
skill_ovos_setup/ovos_skill_setup.egg-info/entry_points.txt
skill_ovos_setup/ovos_skill_setup.egg-info/requires.txt
skill_ovos_setup/ovos_skill_setup.egg-info/top_level.txt
ovos_skill_setup-0.0.1.dist-info/LICENSE
ovos_skill_setup-0.0.1.dist-info/METADATA
ovos_skill_setup-0.0.1.dist-info/WHEEL
ovos_skill_setup-0.0.1.dist-info/entry_points.txt
ovos_skill_setup-0.0.1.dist-info/top_level.txt
ovos_skill_setup-0.0.1.dist-info/RECORD
