Metadata-Version: 2.1
Name: ovos-skill-setup
Version: 0.0.1
Summary: OVOS skill plugin
Home-page: https://github.com/OpenVoiceOS/skill-ovos-setup
Author: JarbasAi
Author-email: jarbasai@mailfence.com
License: Apache-2.0
Keywords: ovos skill plugin
Platform: UNKNOWN
Requires-Dist: ovos-workshop (>=0.0.7a8)
Requires-Dist: ovos-backend-client (>=0.0.6a8,~=0.0)
Requires-Dist: ovos-PHAL-plugin-system (>=0.0.2a5)
Requires-Dist: ovos-plugin-manager (>=0.0.19)
Requires-Dist: ovos-utils (>=0.0.25)
Provides-Extra: plugins
Requires-Dist: ovos-stt-plugin-selene (>=0.0.3a1,~=0.0) ; extra == 'plugins'
Requires-Dist: ovos-stt-plugin-vosk (>=0.1.4a2,~=0.1) ; extra == 'plugins'
Requires-Dist: neon-tts-plugin-larynx-server (~=0.1) ; extra == 'plugins'
Requires-Dist: ovos-tts-plugin-mimic (>=0.2.7post1,~=0.2) ; extra == 'plugins'
Requires-Dist: ovos-tts-plugin-mimic2 (>=0.1.6a4,~=0.1) ; extra == 'plugins'
Requires-Dist: ovos-tts-plugin-pico (>=0.0.4a2,~=0.0) ; extra == 'plugins'
